{
  "ICF": [
    {
      "key": "cdmjcgdwbjcg",
      "value": "cv",
      "id": "1247"
    },
    {
      "id": "f06d",
      "key": "iubuib",
      "value": "knmkj "
    },
    {
      "id": "fd6b",
      "key": "fdmfns",
      "value": "kjbkbsdfsdfsdfs"
    }
  ],
  "Hierarchy": [
    {
      "key": "sdvmsdbn",
      "value": "fsakbvjsnf",
      "id": "1945"
    },
    {
      "id": "954f",
      "key": "fdmfns",
      "value": "svsknm,v"
    },
    {
      "id": "cfc2",
      "key": "cxcx",
      "value": "vxvxx"
    },
    {
      "id": "e48a",
      "key": "sdvmsdbn",
      "value": "sdas"
    }
  ],
  "Default": [
    {
      "key": "khjn",
      "value": "yufkjh",
      "id": "8aa5"
    }
  ]
}